{"Wraps": 1, "Vietnamese": 1, "Ethiopian": 1, "Bagels": 1, "Middle Eastern": 4, "Bakery &amp; Pastries": 3, "Sandwiches": 10, "Korean": 3, "Pizza": 11, "Hoagies": 1, "Late Night": 1, "Deli Food": 4, "Thai": 1, "Cuban": 1, "Healthy": 2, "Burgers": 7, "American": 7, "Coffee &amp; Tea": 2, "Steak": 1, "Ice Cream": 3, "Italian": 3, "Irish": 1, "Mexican": 5, "Subs": 1, "Chinese": 4, "Gyros": 1, "Sushi": 4, "Mediterranean": 1, "Japanese": 2, "Desserts": 2, "Indian": 6, "Asian": 1, "Southwestern": 1, "Barbecue": 1, "Breakfast": 3, "Salads": 1, "Tex-Mex": 1}